INSTALL.rst
LICENSE
MANIFEST.in
README.rst
VERSION
requirements.txt
setup.py
tasks.py
src/flyinthejungle/Background.py
src/flyinthejungle/Box.py
src/flyinthejungle/Drone.py
src/flyinthejungle/GravityItem.py
src/flyinthejungle/Losangle.py
src/flyinthejungle/Main.py
src/flyinthejungle/Services.py
src/flyinthejungle/StarItem.py
src/flyinthejungle/World.py
src/flyinthejungle/__init__.py
src/flyinthejungle/__main__.py
src/flyinthejungle/__meta__.py
src/flyinthejungle.egg-info/PKG-INFO
src/flyinthejungle.egg-info/SOURCES.txt
src/flyinthejungle.egg-info/dependency_links.txt
src/flyinthejungle.egg-info/entry_points.txt
src/flyinthejungle.egg-info/not-zip-safe
src/flyinthejungle.egg-info/requires.txt
src/flyinthejungle.egg-info/top_level.txt
src/flyinthejungle/images/background.jpg
src/flyinthejungle/images/botao_play.png
src/flyinthejungle/images/box.jpg
src/flyinthejungle/images/btnsair.png
src/flyinthejungle/images/c.png
src/flyinthejungle/images/drone_down.png
src/flyinthejungle/images/drone_down_red.png
src/flyinthejungle/images/drone_left.png
src/flyinthejungle/images/drone_left_red.png
src/flyinthejungle/images/drone_right.png
src/flyinthejungle/images/drone_right_red.png
src/flyinthejungle/images/drone_up.png
src/flyinthejungle/images/drone_up_red.png
src/flyinthejungle/images/gravitychange.png
src/flyinthejungle/images/losango.png
src/flyinthejungle/images/star.png
src/flyinthejungle/images/x.gif
src/flyinthejungle/images/z.gif
src/flyinthejungle/sounds/707.wav
src/flyinthejungle/tests/__init__.py
src/flyinthejungle/tests/__main__.py
src/flyinthejungle/tests/test_documentation.py
src/flyinthejungle/tests/test_flyinthejungle.py