Metadata-Version: 1.1
Name: flyinthejungle
Version: 0.1.2
Summary: A game that you need to survive from boxes
Home-page: UNKNOWN
Author: Leonardo A. D. Oliveira
Author-email: leodegolim@yahoo.com.br
License: UNKNOWN
Platform: any
Classifier: Development Status :: 3 - Alpha
Classifier: Intended Audience :: Developers
Classifier: License :: OSI Approved :: GNU General Public License (GPL)
Classifier: Operating System :: OS Independent
Classifier: Programming Language :: Python
Classifier: Programming Language :: Python :: 3
Classifier: Programming Language :: Python :: 3.3
Classifier: Programming Language :: Python :: 3.4
Classifier: Programming Language :: Python :: 3.5
Classifier: Topic :: Software Development :: Libraries
